hpSPMPlusStudio/__init__.py
hpSPMPlusStudio/_version.py
hpSPMPlusStudio/Container/__init__.py
hpSPMPlusStudio/Container/NmiContainer/__init__.py
hpSPMPlusStudio/Container/NmiContainer/container.py
hpSPMPlusStudio/Container/NmiContainer/containerBuilder.py
hpSPMPlusStudio/Container/NmiContainer/enums.py
hpSPMPlusStudio/Container/NmiFrame/__init__.py
hpSPMPlusStudio/Container/NmiFrame/frame.py
hpSPMPlusStudio/Container/NmiFrame/frameChannels.py
hpSPMPlusStudio/Container/NmiImage/__init__.py
hpSPMPlusStudio/Container/NmiImage/image.py
hpSPMPlusStudio/Container/NmiImage/imageBuilder.py
hpSPMPlusStudio/Docs/hpSPMPlus_API_manual_v1.0.2.pdf
hpSPMPlusStudio/ExternalDevices/__init__.py
hpSPMPlusStudio/ExternalDevices/Devices/AndorCamera.py
hpSPMPlusStudio/ExternalDevices/Devices/Thorlabs_SPCM50.py
hpSPMPlusStudio/ExternalDevices/Devices/__init__.py
hpSPMPlusStudio/ExternalDevices/Devices/externalTest.py
hpSPMPlusStudio/ExternalDevices/Devices/utils.py
hpSPMPlusStudio/NMIImporter/BuiltInImporter.py
hpSPMPlusStudio/NMIImporter/Decarators.py
hpSPMPlusStudio/NMIImporter/__init__.py
hpSPMPlusStudio/NMIManager/__init__.py
hpSPMPlusStudio/NMIManager/Managers/CustomScanner.py
hpSPMPlusStudio/NMIManager/Managers/DeviceManager.py
hpSPMPlusStudio/NMIManager/Managers/__init__.py
hpSPMPlusStudio/NMIManager/Managers/Controllers/AdjustFiberController.py
hpSPMPlusStudio/NMIManager/Managers/Controllers/ApproachController.py
hpSPMPlusStudio/NMIManager/Managers/Controllers/AutoTuneController.py
hpSPMPlusStudio/NMIManager/Managers/Controllers/BiasController.py
hpSPMPlusStudio/NMIManager/Managers/Controllers/FiberController.py
hpSPMPlusStudio/NMIManager/Managers/Controllers/HallCardController.py
hpSPMPlusStudio/NMIManager/Managers/Controllers/OptionsController.py
hpSPMPlusStudio/NMIManager/Managers/Controllers/PIDController.py
hpSPMPlusStudio/NMIManager/Managers/Controllers/PhotoDiodeController.py
hpSPMPlusStudio/NMIManager/Managers/Controllers/ScanController.py
hpspmplusstudio-1.0.7.dist-info/METADATA
hpspmplusstudio-1.0.7.dist-info/WHEEL
hpspmplusstudio-1.0.7.dist-info/top_level.txt
hpspmplusstudio-1.0.7.dist-info/RECORD
