Metadata-Version: 2.1
Name: hpspmplusstudio
Version: 1.0.7
Author: NanoMagnetics Instruments
Author-email: nmi.swteam@nano.com.tr
Classifier: Programming Language :: Python :: 3
Classifier: License :: OSI Approved :: MIT License
Classifier: Operating System :: OS Independent
Requires-Python: >=3.6
Requires-Dist: certifi==2024.12.14
Requires-Dist: charset-normalizer==3.4.1
Requires-Dist: colorama==0.4.6
Requires-Dist: contourpy==1.3.1
Requires-Dist: cycler==0.12.1
Requires-Dist: fonttools==4.55.3
Requires-Dist: idna==3.10
Requires-Dist: kiwisolver==1.4.8
Requires-Dist: matplotlib==3.10.0
Requires-Dist: numpy==2.2.1
Requires-Dist: packaging==24.2
Requires-Dist: pillow==11.1.0
Requires-Dist: pyparsing==3.2.1
Requires-Dist: python-dateutil==2.9.0.post0
Requires-Dist: PyVISA==1.14.1
Requires-Dist: requests==2.32.3
Requires-Dist: six==1.17.0
Requires-Dist: tqdm==4.67.1
Requires-Dist: typing-extensions==4.12.2
Requires-Dist: urllib3==2.3.0
